func_adl/__init__.py
func_adl/event_dataset.py
func_adl/functions.py
func_adl/object_stream.py
func_adl/util_ast.py
func_adl/ast/__init__.py
func_adl/ast/aggregate_shortcuts.py
func_adl/ast/ast_hash.py
func_adl/ast/call_stack.py
func_adl/ast/func_adl_ast_utils.py
func_adl/ast/function_simplifier.py
func_adl.ast-2.3.1.dist-info/METADATA
func_adl.ast-2.3.1.dist-info/WHEEL
func_adl.ast-2.3.1.dist-info/top_level.txt
func_adl.ast-2.3.1.dist-info/RECORD
