Metadata-Version: 2.1
Name: func-adl.ast
Version: 2.3.1
Summary: Functional Analysis Description Language - Backend AST Manipulation Packages
Home-page: https://github.com/iris-hep/func_adl
Author: G. Watts (IRIS-HEP/UW Seattle)
Author-email: gwatts@uw.edu
Maintainer: Gordon Watts (IRIS-HEP/UW Seattle)
Maintainer-email: gwatts@uw.edu
License: TBD
Platform: Any
Classifier: Intended Audience :: Developers
Classifier: Intended Audience :: Information Technology
Classifier: Programming Language :: Python
Classifier: Programming Language :: Python :: 3.9
Classifier: Programming Language :: Python :: 3.8
Classifier: Programming Language :: Python :: 3.6
Classifier: Programming Language :: Python :: 3.7
Classifier: Programming Language :: Python :: 3.6
Classifier: Topic :: Software Development
Classifier: Topic :: Utilities
Requires-Python: >=3.6, <3.11
Requires-Dist: func-adl (==2.3.1)
Provides-Extra: complete
Requires-Dist: coverage ; extra == 'complete'
Requires-Dist: flake8 ; extra == 'complete'
Requires-Dist: pytest ; extra == 'complete'
Requires-Dist: pytest-cov ; extra == 'complete'
Requires-Dist: twine ; extra == 'complete'
Provides-Extra: develop
Requires-Dist: pytest ; extra == 'develop'
Requires-Dist: pytest-cov ; extra == 'develop'
Requires-Dist: flake8 ; extra == 'develop'
Requires-Dist: coverage ; extra == 'develop'
Requires-Dist: twine ; extra == 'develop'
